MANIFEST.in
README
REQUIREMENTS
distribute_setup.py
setup.py
src/django_compass2.egg-info/PKG-INFO
src/django_compass2.egg-info/SOURCES.txt
src/django_compass2.egg-info/dependency_links.txt
src/django_compass2.egg-info/top_level.txt
src/djcompass/__init__.py
src/djcompass/models.py
src/djcompass/management/__init__.py
src/djcompass/management/commands/__init__.py
src/djcompass/management/commands/compass.py