Metadata-Version: 1.0
Name: django-compass2
Version: 0.2
Summary: Simple compilation of Compass projects for Django.
Home-page: http://bitbucket.org/slafs/django-compass2
Author: Slawomir Ehlert
Author-email: slafs.e@gmail.com
License: UNKNOWN
Platform: UNKNOWN
